ssf_downloader/__init__.py
ssf_downloader/client.py
ssf_downloader/models.py
ssf_downloader/scripts/__init__.py
ssf_downloader/scripts/ssf_downloader.py
77file_downloader-1.0.1.dist-info/METADATA
77file_downloader-1.0.1.dist-info/WHEEL
77file_downloader-1.0.1.dist-info/entry_points.txt
77file_downloader-1.0.1.dist-info/top_level.txt
77file_downloader-1.0.1.dist-info/RECORD
