Metadata-Version: 2.1
Name: 77file-downloader
Version: 1.0.1
Summary: Simple downloader for 77file.com website
Author: Bayu Ganteng
Author-email: Bayu Ganteng <getkilla5@gmail.com>
Project-URL: Homepage, https://github.com/bayy420-999/ssf-downloader
Keywords: 77file,downloader,cloudstorage
Classifier: License :: OSI Approved :: MIT License
Classifier: Programming Language :: Python
Classifier: Programming Language :: Python :: 3
Requires-Python: >=3.9
Requires-Dist: aiohttp
Requires-Dist: cloudscraper
Requires-Dist: bs4
Provides-Extra: dev
Requires-Dist: black ; extra == 'dev'
Requires-Dist: bumpver ; extra == 'dev'
Requires-Dist: isort ; extra == 'dev'
Requires-Dist: pip-tools ; extra == 'dev'
Requires-Dist: pytest ; extra == 'dev'
